graph_validation_tests/__init__.py
graph_validation_tests/translator/__init__.py
graph_validation_tests/translator/registry/__init__.py
graph_validation_tests/translator/trapi/__init__.py
graph_validation_tests/utils/__init__.py
graph_validation_tests/utils/asyncio.py
graph_validation_tests/utils/constants.py
graph_validation_tests/utils/unit_test_templates.py
one_hop_test_runner/__init__.py
standards_validation_test_runner/__init__.py
graph_validation_test_runners-0.1.5.dist-info/LICENSE
graph_validation_test_runners-0.1.5.dist-info/METADATA
graph_validation_test_runners-0.1.5.dist-info/WHEEL
graph_validation_test_runners-0.1.5.dist-info/entry_points.txt
graph_validation_test_runners-0.1.5.dist-info/RECORD
