Metadata-Version: 2.1
Name: graph-validation-test-runners
Version: 0.1.5
Summary: Validation of Translator Knowledge Graphs - TRAPI, Biolink Model and One Hop navigation
Home-page: https://github.com/TranslatorSRI
License: MIT
Keywords: NCATS,Biomedical Data Translator,Translator,ReasonerAPI,TRAPI,validation,Biolink Model
Author: Richard Bruskiewich
Author-email: richard.bruskiewich@delphinai.com
Maintainer: Richard Bruskiewich
Maintainer-email: richard.bruskiewich@delphinai.com
Requires-Python: >=3.9,<3.12
Classifier: Intended Audience :: Developers
Classifier: Intended Audience :: Healthcare Industry
Classifier: Intended Audience :: Science/Research
Classifier: License :: OSI Approved :: MIT License
Classifier: Operating System :: OS Independent
Classifier: Programming Language :: Python :: 3
Classifier: Programming Language :: Python :: 3.9
Classifier: Programming Language :: Python :: 3.10
Classifier: Programming Language :: Python :: 3.11
Classifier: Topic :: Scientific/Engineering :: Bio-Informatics
Classifier: Topic :: Software Development :: Libraries :: Python Modules
Requires-Dist: deepdiff (>=7.0.1,<8.0.0)
Requires-Dist: fastapi
Requires-Dist: httpx (>=0.27.0,<0.28.0)
Requires-Dist: matplotlib (>=3.8.3,<4.0.0)
Requires-Dist: reasoner-validator (>=4.2.5,<5.0.0)
Requires-Dist: requests (>=2.31.0,<3.0.0)
Requires-Dist: tqdm (>=4.66.2,<5.0.0)
Requires-Dist: translator-testing-model (>=0.3.1,<0.4.0)
Project-URL: Bug Tracker, https://github.com/TranslatorSRI/graph-validation-test-runners/issues
Project-URL: Change Log, https://github.com/TranslatorSRI/graph-validation-test-runners/blob/master/CHANGELOG.md
Project-URL: Documentation, https://github.com/TranslatorSRI/graph-validation-test-runners/blob/main/README.md
Project-URL: Repository, https://github.com/TranslatorSRI/graph-validation-test-runners
